[
  {
    "Type": "DataTable",
    "Name": "LoginWelcomeVoice",
    "Class": "UScriptClass'DataTable'",
    "Properties": {
      "RowStruct": {
        "ObjectName": "ScriptStruct'CyLoginWelcomeVoiceTableRow'",
        "ObjectPath": "/Script/PMGame"
      }
    },
    "Rows": {
      "1": {
        "VoiceId": 22101022
      },
      "2": {
        "VoiceId": 22132022
      },
      "3": {
        "VoiceId": 22107022
      },
      "4": {
        "VoiceId": 22128022
      },
      "5": {
        "VoiceId": 22146022
      },
      "6": {
        "VoiceId": 22112022
      },
      "7": {
        "VoiceId": 22133022
      },
      "8": {
        "VoiceId": 22105022
      },
      "9": {
        "VoiceId": 22124022
      },
      "10": {
        "VoiceId": 22131022
      },
      "11": {
        "VoiceId": 22137022
      }
    }
  }
]