[
  {
    "Type": "DataTable",
    "Name": "DT_Guide_TeamGuide_Dialogue",
    "Class": "UScriptClass'DataTable'",
    "Properties": {
      "RowStruct": {
        "ObjectName": "ScriptStruct'CyGuideDialogueConfig'",
        "ObjectPath": "/Script/PMGame"
      }
    },
    "Rows": {
      "1": {
        "DialogueId": 4101,
        "bShow": true,
        "bAllowSkip": true,
        "bFlickerHead": false,
        "RoleId": 146,
        "Text": {
          "Namespace": "",
          "Key": "8C961BA3491F7BC46564D6BB26076954",
          "SourceString": "还好赶上了……",
          "LocalizedString": "还好赶上了……"
        },
        "AkOnEvent": {
          "AssetPathName": "None",
          "SubPathString": ""
        },
        "Time": 4.0,
        "TriggerEvents": [
          {
            "UniqueName": "3",
            "EventGameplayTag": {
              "TagName": "None"
            },
            "EventType": "ECyGuideEventType::GuideTask",
            "WeaponEventType": "ECyGuideWeaponEventType::None",
            "GuideStateType": "ECyGuideStateType::None",
            "GuideTaskStateType": "ECyGuideTaskStateType::Begin",
            "GuideSubTaskStateType": "ECyGuideSubTaskStateType::None",
            "GuideDialogueStateType": "ECyGuideDialogueStateType::None",
            "GuideTriggerAreaType": "ECyGuideTriggerAreaType::None",
            "GuideEnemyEventType": "ECyGuideEnemyEventType::None",
            "SequenceStateType": "ECySequenceStateType::None",
            "ActionType": "ECyGuideActionType::None",
            "MeshModeType": "EMeshModeType::Normal",
            "GameStateType": "EGStateType::None",
            "EquipmentSlotType": "ECyGuideEquipmentSlotType::None"
          }
        ],
        "RoleNameColor": {
          "SpecifiedColor": {
            "R": 1.0,
            "G": 0.0,
            "B": 1.0,
            "A": 1.0,
            "Hex": "FFFF00FF"
          },
          "ColorUseRule": "ESlateColorStylingMode::UseColor_Specified"
        }
      },
      "2": {
        "DialogueId": 2,
        "bShow": true,
        "bAllowSkip": true,
        "bFlickerHead": false,
        "RoleId": 108,
        "Text": {
          "Namespace": "",
          "Key": "AEAD645C43992CA1FB2FE892980905F7",
          "SourceString": "来得正好，有了你的增援，我们的胜算又多了几分。",
          "LocalizedString": "来得正好，有了你的增援，我们的胜算又多了几分。"
        },
        "AkOnEvent": {
          "AssetPathName": "None",
          "SubPathString": ""
        },
        "Time": 6.0,
        "TriggerEvents": [
          {
            "UniqueName": "4101",
            "EventGameplayTag": {
              "TagName": "None"
            },
            "EventType": "ECyGuideEventType::GuideDialogue",
            "WeaponEventType": "ECyGuideWeaponEventType::None",
            "GuideStateType": "ECyGuideStateType::None",
            "GuideTaskStateType": "ECyGuideTaskStateType::None",
            "GuideSubTaskStateType": "ECyGuideSubTaskStateType::None",
            "GuideDialogueStateType": "ECyGuideDialogueStateType::End",
            "GuideTriggerAreaType": "ECyGuideTriggerAreaType::None",
            "GuideEnemyEventType": "ECyGuideEnemyEventType::None",
            "SequenceStateType": "ECySequenceStateType::None",
            "ActionType": "ECyGuideActionType::None",
            "MeshModeType": "EMeshModeType::Normal",
            "GameStateType": "EGStateType::None",
            "EquipmentSlotType": "ECyGuideEquipmentSlotType::None"
          }
        ],
        "RoleNameColor": {
          "SpecifiedColor": {
            "R": 1.0,
            "G": 0.0,
            "B": 1.0,
            "A": 1.0,
            "Hex": "FFFF00FF"
          },
          "ColorUseRule": "ESlateColorStylingMode::UseColor_Specified"
        }
      },
      "3": {
        "DialogueId": 3,
        "bShow": true,
        "bAllowSkip": true,
        "bFlickerHead": false,
        "RoleId": 146,
        "Text": {
          "Namespace": "",
          "Key": "B8CB17B94C90E3EFA9D213B2625A86C1",
          "SourceString": "我已经准备好了，如果需要支援的话，请随时呼唤我。",
          "LocalizedString": "我已经准备好了，如果需要支援的话，请随时呼唤我。"
        },
        "AkOnEvent": {
          "AssetPathName": "None",
          "SubPathString": ""
        },
        "Time": 6.0,
        "TriggerEvents": [
          {
            "UniqueName": "2",
            "EventGameplayTag": {
              "TagName": "None"
            },
            "EventType": "ECyGuideEventType::GuideDialogue",
            "WeaponEventType": "ECyGuideWeaponEventType::None",
            "GuideStateType": "ECyGuideStateType::None",
            "GuideTaskStateType": "ECyGuideTaskStateType::None",
            "GuideSubTaskStateType": "ECyGuideSubTaskStateType::None",
            "GuideDialogueStateType": "ECyGuideDialogueStateType::End",
            "GuideTriggerAreaType": "ECyGuideTriggerAreaType::None",
            "GuideEnemyEventType": "ECyGuideEnemyEventType::None",
            "SequenceStateType": "ECySequenceStateType::None",
            "ActionType": "ECyGuideActionType::None",
            "MeshModeType": "EMeshModeType::Normal",
            "GameStateType": "EGStateType::None",
            "EquipmentSlotType": "ECyGuideEquipmentSlotType::None"
          }
        ],
        "RoleNameColor": {
          "SpecifiedColor": {
            "R": 1.0,
            "G": 0.0,
            "B": 1.0,
            "A": 1.0,
            "Hex": "FFFF00FF"
          },
          "ColorUseRule": "ESlateColorStylingMode::UseColor_Specified"
        }
      },
      "4": {
        "DialogueId": 4,
        "bShow": true,
        "bAllowSkip": true,
        "bFlickerHead": false,
        "RoleId": 108,
        "Text": {
          "Namespace": "",
          "Key": "3F4B7FD8464BA1BAC95E358EAF91230A",
          "SourceString": "目标是摧毁50副卡丘身，开始行动！",
          "LocalizedString": "目标是摧毁50副卡丘身，开始行动！"
        },
        "AkOnEvent": {
          "AssetPathName": "None",
          "SubPathString": ""
        },
        "Time": 5.0,
        "TriggerEvents": [
          {
            "UniqueName": "3",
            "EventGameplayTag": {
              "TagName": "None"
            },
            "EventType": "ECyGuideEventType::GuideDialogue",
            "WeaponEventType": "ECyGuideWeaponEventType::None",
            "GuideStateType": "ECyGuideStateType::None",
            "GuideTaskStateType": "ECyGuideTaskStateType::None",
            "GuideSubTaskStateType": "ECyGuideSubTaskStateType::None",
            "GuideDialogueStateType": "ECyGuideDialogueStateType::End",
            "GuideTriggerAreaType": "ECyGuideTriggerAreaType::None",
            "GuideEnemyEventType": "ECyGuideEnemyEventType::None",
            "SequenceStateType": "ECySequenceStateType::None",
            "ActionType": "ECyGuideActionType::None",
            "MeshModeType": "EMeshModeType::Normal",
            "GameStateType": "EGStateType::None",
            "EquipmentSlotType": "ECyGuideEquipmentSlotType::None"
          }
        ],
        "RoleNameColor": {
          "SpecifiedColor": {
            "R": 1.0,
            "G": 0.0,
            "B": 1.0,
            "A": 1.0,
            "Hex": "FFFF00FF"
          },
          "ColorUseRule": "ESlateColorStylingMode::UseColor_Specified"
        }
      },
      "5": {
        "DialogueId": 41010,
        "bShow": true,
        "bAllowSkip": true,
        "bFlickerHead": false,
        "RoleId": 146,
        "Text": {
          "Namespace": "",
          "Key": "8C961BA3491F7BC46564D6BB26076954",
          "SourceString": "还好赶上了……",
          "LocalizedString": "还好赶上了……"
        },
        "AkOnEvent": {
          "AssetPathName": "None",
          "SubPathString": ""
        },
        "Time": 4.0,
        "TriggerEvents": [
          {
            "UniqueName": "30",
            "EventGameplayTag": {
              "TagName": "None"
            },
            "EventType": "ECyGuideEventType::GuideTask",
            "WeaponEventType": "ECyGuideWeaponEventType::None",
            "GuideStateType": "ECyGuideStateType::None",
            "GuideTaskStateType": "ECyGuideTaskStateType::Begin",
            "GuideSubTaskStateType": "ECyGuideSubTaskStateType::None",
            "GuideDialogueStateType": "ECyGuideDialogueStateType::None",
            "GuideTriggerAreaType": "ECyGuideTriggerAreaType::None",
            "GuideEnemyEventType": "ECyGuideEnemyEventType::None",
            "SequenceStateType": "ECySequenceStateType::None",
            "ActionType": "ECyGuideActionType::None",
            "MeshModeType": "EMeshModeType::Normal",
            "GameStateType": "EGStateType::None",
            "EquipmentSlotType": "ECyGuideEquipmentSlotType::None"
          }
        ],
        "RoleNameColor": {
          "SpecifiedColor": {
            "R": 1.0,
            "G": 0.0,
            "B": 1.0,
            "A": 1.0,
            "Hex": "FFFF00FF"
          },
          "ColorUseRule": "ESlateColorStylingMode::UseColor_Specified"
        }
      },
      "6": {
        "DialogueId": 20,
        "bShow": true,
        "bAllowSkip": true,
        "bFlickerHead": false,
        "RoleId": 108,
        "Text": {
          "Namespace": "",
          "Key": "AEAD645C43992CA1FB2FE892980905F7",
          "SourceString": "来得正好，有了你的增援，我们的胜算又多了几分。",
          "LocalizedString": "来得正好，有了你的增援，我们的胜算又多了几分。"
        },
        "AkOnEvent": {
          "AssetPathName": "None",
          "SubPathString": ""
        },
        "Time": 6.0,
        "TriggerEvents": [
          {
            "UniqueName": "41010",
            "EventGameplayTag": {
              "TagName": "None"
            },
            "EventType": "ECyGuideEventType::GuideDialogue",
            "WeaponEventType": "ECyGuideWeaponEventType::None",
            "GuideStateType": "ECyGuideStateType::None",
            "GuideTaskStateType": "ECyGuideTaskStateType::None",
            "GuideSubTaskStateType": "ECyGuideSubTaskStateType::None",
            "GuideDialogueStateType": "ECyGuideDialogueStateType::End",
            "GuideTriggerAreaType": "ECyGuideTriggerAreaType::None",
            "GuideEnemyEventType": "ECyGuideEnemyEventType::None",
            "SequenceStateType": "ECySequenceStateType::None",
            "ActionType": "ECyGuideActionType::None",
            "MeshModeType": "EMeshModeType::Normal",
            "GameStateType": "EGStateType::None",
            "EquipmentSlotType": "ECyGuideEquipmentSlotType::None"
          }
        ],
        "RoleNameColor": {
          "SpecifiedColor": {
            "R": 1.0,
            "G": 0.0,
            "B": 1.0,
            "A": 1.0,
            "Hex": "FFFF00FF"
          },
          "ColorUseRule": "ESlateColorStylingMode::UseColor_Specified"
        }
      },
      "7": {
        "DialogueId": 30,
        "bShow": true,
        "bAllowSkip": true,
        "bFlickerHead": false,
        "RoleId": 146,
        "Text": {
          "Namespace": "",
          "Key": "B8CB17B94C90E3EFA9D213B2625A86C1",
          "SourceString": "我已经准备好了，如果需要支援的话，请随时呼唤我。",
          "LocalizedString": "我已经准备好了，如果需要支援的话，请随时呼唤我。"
        },
        "AkOnEvent": {
          "AssetPathName": "None",
          "SubPathString": ""
        },
        "Time": 6.0,
        "TriggerEvents": [
          {
            "UniqueName": "20",
            "EventGameplayTag": {
              "TagName": "None"
            },
            "EventType": "ECyGuideEventType::GuideDialogue",
            "WeaponEventType": "ECyGuideWeaponEventType::None",
            "GuideStateType": "ECyGuideStateType::None",
            "GuideTaskStateType": "ECyGuideTaskStateType::None",
            "GuideSubTaskStateType": "ECyGuideSubTaskStateType::None",
            "GuideDialogueStateType": "ECyGuideDialogueStateType::End",
            "GuideTriggerAreaType": "ECyGuideTriggerAreaType::None",
            "GuideEnemyEventType": "ECyGuideEnemyEventType::None",
            "SequenceStateType": "ECySequenceStateType::None",
            "ActionType": "ECyGuideActionType::None",
            "MeshModeType": "EMeshModeType::Normal",
            "GameStateType": "EGStateType::None",
            "EquipmentSlotType": "ECyGuideEquipmentSlotType::None"
          }
        ],
        "RoleNameColor": {
          "SpecifiedColor": {
            "R": 1.0,
            "G": 0.0,
            "B": 1.0,
            "A": 1.0,
            "Hex": "FFFF00FF"
          },
          "ColorUseRule": "ESlateColorStylingMode::UseColor_Specified"
        }
      },
      "8": {
        "DialogueId": 40,
        "bShow": true,
        "bAllowSkip": true,
        "bFlickerHead": false,
        "RoleId": 108,
        "Text": {
          "Namespace": "",
          "Key": "8CBFBE79458C4DEC2D18428A1EEAFC34",
          "SourceString": "目标是摧毁30副卡丘身，开始行动！",
          "LocalizedString": "目标是摧毁30副卡丘身，开始行动！"
        },
        "AkOnEvent": {
          "AssetPathName": "None",
          "SubPathString": ""
        },
        "Time": 5.0,
        "TriggerEvents": [
          {
            "UniqueName": "30",
            "EventGameplayTag": {
              "TagName": "None"
            },
            "EventType": "ECyGuideEventType::GuideDialogue",
            "WeaponEventType": "ECyGuideWeaponEventType::None",
            "GuideStateType": "ECyGuideStateType::None",
            "GuideTaskStateType": "ECyGuideTaskStateType::None",
            "GuideSubTaskStateType": "ECyGuideSubTaskStateType::None",
            "GuideDialogueStateType": "ECyGuideDialogueStateType::End",
            "GuideTriggerAreaType": "ECyGuideTriggerAreaType::None",
            "GuideEnemyEventType": "ECyGuideEnemyEventType::None",
            "SequenceStateType": "ECySequenceStateType::None",
            "ActionType": "ECyGuideActionType::None",
            "MeshModeType": "EMeshModeType::Normal",
            "GameStateType": "EGStateType::None",
            "EquipmentSlotType": "ECyGuideEquipmentSlotType::None"
          }
        ],
        "RoleNameColor": {
          "SpecifiedColor": {
            "R": 1.0,
            "G": 0.0,
            "B": 1.0,
            "A": 1.0,
            "Hex": "FFFF00FF"
          },
          "ColorUseRule": "ESlateColorStylingMode::UseColor_Specified"
        }
      }
    }
  }
]