[
  {
    "Type": "StringTable",
    "Name": "ST_Chat",
    "Class": "UScriptClass'StringTable'",
    "StringTable": {
      "TableNamespace": "ST_Store",
      "KeysToMetaData": {
        "WorldChatTabName": "世界",
        "ChatTargetFormat": "对【{0}】说：",
        "ChatNick": "{0}：",
        "ChatCoolDownTip": "可发送至该频道的信息数量有限，请稍后再试~",
        "NewChatMsgNum": "{0} 条新消息",
        "SystemChatTabName": "系统",
        "ChatTitle": "【{0}】",
        "PrivateChatTabName": "私聊",
        "MatchChatTabName": "比赛",
        "TeamChatTabName": "队伍",
        "GoToChatBottom": "回到底部",
        "Friend": "好友",
        "Nearest": "最近",
        "Chat_MarkPoint": "{PlayerName} [{RoleName}] 发出{MarkPointName}——{AreaName}",
        "Chat_Disconnect": "{PlayerName} [{RoleName}] 已断开连接",
        "Chat_Reconnect": "{PlayerName} [{RoleName}] 已回归",
        "Chat_QuitGame": "{PlayerName} [{RoleName}] 已退出房间",
        "Chat_HostedByAI": "{PlayerName} [{RoleName}] 自动被智能托管",
        "Chat_Disconnect_NoRoleName": "{PlayerName}已断开连接",
        "Chat_HostedByAI_NoRoleName": "{PlayerName}自动被智能托管",
        "Chat_QuitGame_NoRoleName": "{PlayerName}已退出房间",
        "Chat_Reconnect_NoRoleName": "{PlayerName}已回归",
        "ChatNickHyper": "<a id=\"Chat\" style=\"Chat\">{0}</>：",
        "ChatTeamHyper": "快来一起开黑：<a id=\"Team\" style=\"Team\" teamID=\"{0}\" UID=\"{1}\">我的队伍</>",
        "TeamHyperToolTipText_Self": "其他玩家点击这个链接能加入你的队伍",
        "TeamHyperToolTipText_Other": "点击这个链接能加入发布玩家的队伍",
        "ChatPlayerInfoHyper": "请点击 [<a id=\"Player\" style=\"Player\" playerUID=\"{0}\" Nick=\"{1}\">{2}</>] 加我好友",
        "Chat_JoinTeamApply": "已发送加入队伍请求",
        "WorldChatLevelLimit": "您需要达到{0}级后才能在世界频道发言哦",
        "TeamInvalid": "队伍不存在",
        "ShieldChatMsg": "已屏蔽玩家 {0}",
        "ChatPlayerInfoHyper_MB": "请点击 [<a id=\"Player\" style=\"Player_MB\" playerUID=\"{0}\" Nick=\"{1}\">{2}</>] 加我好友",
        "ChatTeamHyper_MB": "快来一起开黑：<a id=\"Team\" style=\"Team_MB\" teamID=\"{0}\" UID=\"{1}\">我的队伍</>",
        "ForbidChatHint": "您的账号因{0}被禁止发言，预计{1}解禁",
        "ForbidPlayerMsg": "已屏蔽其文字语音信号",
        "ChatEmotionFormat": "[style=\"Image\" id=\"#{0}\"]",
        "WorldChannelChangeSucceed": "已切换至频道{0}",
        "WorldChatChannel": "世界频道{0}",
        "TeamVoiceDisableTip": "该模式无法使用队伍频道",
        "RoleName_Spectator": "观战者",
        "UnshieldChatMsg": "已解除对玩家 {0} 的屏蔽"
      }
    },
    "StringTableId": 0
  }
]