[
  {
    "Type": "DataTable",
    "Name": "AVGRole",
    "Class": "UScriptClass'DataTable'",
    "Properties": {
      "RowStruct": {
        "ObjectName": "ScriptStruct'CyAVGRoleTableRow'",
        "ObjectPath": "/Script/PMGame"
      },
      "bIgnoreExtraFields": true,
      "bIgnoreMissingFields": true
    },
    "Rows": {
      "105": {
        "RoleId": 105,
        "Camp": 3,
        "ModelAsset": {
          "AssetPathName": "/Game/PaperMan/SkinAssets/Characters/Audrey/S201/Mesh3DLobby/Audrey_Mesh_201.Audrey_Mesh_201",
          "SubPathString": ""
        }
      },
      "133": {
        "RoleId": 133,
        "Camp": 2,
        "ModelAsset": {
          "AssetPathName": "None",
          "SubPathString": ""
        }
      },
      "101": {
        "RoleId": 101,
        "Camp": 1,
        "ModelAsset": {
          "AssetPathName": "/Game/PaperMan/SkinAssets/Characters/Michele/S201/Mesh3DLobby/Michel_Mesh_201_Lobby.Michel_Mesh_201_Lobby",
          "SubPathString": ""
        }
      },
      "132": {
        "RoleId": 132,
        "Camp": 2,
        "ModelAsset": {
          "AssetPathName": "/Game/PaperMan/SkinAssets/Characters/HuiXing/S201/Mesh3DLobby/HuiXing_Model_Lobby_201.HuiXing_Model_Lobby_201",
          "SubPathString": ""
        }
      },
      "146": {
        "RoleId": 146,
        "Camp": 3,
        "ModelAsset": {
          "AssetPathName": "/Game/PaperMan/SkinAssets/Characters/HuiXing/S201/Mesh3DLobby/HuiXing_Model_Lobby_201.HuiXing_Model_Lobby_201",
          "SubPathString": ""
        }
      },
      "124": {
        "RoleId": 124,
        "Camp": 1,
        "ModelAsset": {
          "AssetPathName": "None",
          "SubPathString": ""
        }
      },
      "110": {
        "RoleId": 110,
        "Camp": 3,
        "ModelAsset": {
          "AssetPathName": "None",
          "SubPathString": ""
        }
      },
      "131": {
        "RoleId": 131,
        "Camp": 1,
        "ModelAsset": {
          "AssetPathName": "None",
          "SubPathString": ""
        }
      },
      "109": {
        "RoleId": 109,
        "Camp": 2,
        "ModelAsset": {
          "AssetPathName": "None",
          "SubPathString": ""
        }
      }
    }
  }
]